l_sys/__init__.py
l_sys/l_sys.py
l_sys-1.1.2.dist-info/METADATA
l_sys-1.1.2.dist-info/WHEEL
l_sys-1.1.2.dist-info/top_level.txt
l_sys-1.1.2.dist-info/RECORD
