Metadata-Version: 2.1
Name: l-sys
Version: 1.1.2
Summary: L-Systems
Home-page: https://github.com/MrZloHex/l-sys
Author: MrZloHex
Author-email: zlo.alex.it@gmail.com
License: MIT
Platform: UNKNOWN
Classifier: License :: OSI Approved :: MIT License
Classifier: Programming Language :: Python
Classifier: Programming Language :: Python :: 3
Classifier: Programming Language :: Python :: 3.6
Classifier: Programming Language :: Python :: 3.7
Classifier: Programming Language :: Python :: 3.8
Classifier: Programming Language :: Python :: 3.9
Classifier: Operating System :: OS Independent
